{
  "$schema": "https://developer.microsoft.com/json-schemas/fabric/item/report/definition/visualContainer/1.7.0/schema.json",
  "name": "352bd11f891b86b53612",
  "position": {
    "x": 731,
    "y": 421,
    "z": 12000,
    "height": 282,
    "width": 539,
    "tabOrder": 12000
  },
  "visual": {
    "visualType": "clusteredBarChart",
    "query": {
      "queryState": {
        "Category": {
          "projections": [
            {
              "field": {
                "Column": {
                  "Expression": {
                    "SourceRef": {
                      "Entity": "Mostaql_Skills"
                    }
                  },
                  "Property": "Tags_en"
                }
              },
              "queryRef": "Mostaql_Skills.Tags_en",
              "nativeQueryRef": "Count of Tags_en",
              "active": true
            }
          ]
        },
        "Y": {
          "projections": [
            {
              "field": {
                "Aggregation": {
                  "Expression": {
                    "Column": {
                      "Expression": {
                        "SourceRef": {
                          "Entity": "Mostaql_Skills"
                        }
                      },
                      "Property": "Tags_en"
                    }
                  },
                  "Function": 5
                }
              },
              "queryRef": "CountNonNull(Mostaql_Skills.Tags_en)",
              "nativeQueryRef": "Count of Tags_en1"
            }
          ]
        }
      },
      "sortDefinition": {
        "sort": [
          {
            "field": {
              "Aggregation": {
                "Expression": {
                  "Column": {
                    "Expression": {
                      "SourceRef": {
                        "Entity": "Mostaql_Skills"
                      }
                    },
                    "Property": "Tags_en"
                  }
                },
                "Function": 5
              }
            },
            "direction": "Descending"
          }
        ],
        "isDefaultSort": true
      }
    },
    "objects": {
      "legend": [
        {
          "properties": {
            "show": {
              "expr": {
                "Literal": {
                  "Value": "false"
                }
              }
            },
            "showGradientLegend": {
              "expr": {
                "Literal": {
                  "Value": "false"
                }
              }
            }
          }
        }
      ],
      "categoryAxis": [
        {
          "properties": {
            "concatenateLabels": {
              "expr": {
                "Literal": {
                  "Value": "false"
                }
              }
            },
            "fontFamily": {
              "expr": {
                "Literal": {
                  "Value": "'Arial'"
                }
              }
            },
            "fontSize": {
              "expr": {
                "Literal": {
                  "Value": "10D"
                }
              }
            },
            "labelColor": {
              "solid": {
                "color": {
                  "expr": {
                    "Literal": {
                      "Value": "'#644F22'"
                    }
                  }
                }
              }
            },
            "titleFontFamily": {
              "expr": {
                "Literal": {
                  "Value": "'Arial'"
                }
              }
            },
            "titleFontSize": {
              "expr": {
                "Literal": {
                  "Value": "14D"
                }
              }
            },
            "titleBold": {
              "expr": {
                "Literal": {
                  "Value": "false"
                }
              }
            },
            "titleColor": {
              "solid": {
                "color": {
                  "expr": {
                    "Literal": {
                      "Value": "'#3C2F13'"
                    }
                  }
                }
              }
            },
            "switchAxisPosition": {
              "expr": {
                "Literal": {
                  "Value": "true"
                }
              }
            },
            "titleText": {
              "expr": {
                "Literal": {
                  "Value": "'المهارات'"
                }
              }
            }
          }
        }
      ],
      "valueAxis": [
        {
          "properties": {
            "invertAxis": {
              "expr": {
                "Literal": {
                  "Value": "true"
                }
              }
            },
            "fontFamily": {
              "expr": {
                "Literal": {
                  "Value": "'Arial'"
                }
              }
            },
            "fontSize": {
              "expr": {
                "Literal": {
                  "Value": "10D"
                }
              }
            },
            "labelColor": {
              "solid": {
                "color": {
                  "expr": {
                    "Literal": {
                      "Value": "'#644F22'"
                    }
                  }
                }
              }
            },
            "titleFontFamily": {
              "expr": {
                "Literal": {
                  "Value": "'Arial'"
                }
              }
            },
            "titleFontSize": {
              "expr": {
                "Literal": {
                  "Value": "14D"
                }
              }
            },
            "titleColor": {
              "solid": {
                "color": {
                  "expr": {
                    "Literal": {
                      "Value": "'#3C2F13'"
                    }
                  }
                }
              }
            },
            "gridlineColor": {
              "solid": {
                "color": {
                  "expr": {
                    "Literal": {
                      "Value": "'#3C2F13'"
                    }
                  }
                }
              }
            },
            "titleText": {
              "expr": {
                "Literal": {
                  "Value": "'عدد مرات الطلب'"
                }
              }
            }
          }
        }
      ],
      "dataPoint": [
        {
          "properties": {
            "fill": {
              "solid": {
                "color": {
                  "expr": {
                    "FillRule": {
                      "Input": {
                        "Aggregation": {
                          "Expression": {
                            "Column": {
                              "Expression": {
                                "SourceRef": {
                                  "Entity": "Mostaql_Skills"
                                }
                              },
                              "Property": "Tags_en"
                            }
                          },
                          "Function": 5
                        }
                      },
                      "FillRule": {
                        "linearGradient2": {
                          "min": {
                            "color": {
                              "Literal": {
                                "Value": "'#FBABB1'"
                              }
                            }
                          },
                          "max": {
                            "color": {
                              "Literal": {
                                "Value": "'#390006'"
                              }
                            }
                          },
                          "nullColoringStrategy": {
                            "strategy": {
                              "Literal": {
                                "Value": "'asZero'"
                              }
                            }
                          }
                        }
                      }
                    }
                  }
                }
              }
            }
          },
          "selector": {
            "data": [
              {
                "dataViewWildcard": {
                  "matchingOption": 1
                }
              }
            ]
          }
        },
        {
          "properties": {
            "fill": {
              "solid": {
                "color": {
                  "expr": {
                    "Literal": {
                      "Value": "'#4B0B19'"
                    }
                  }
                }
              }
            }
          },
          "selector": {
            "data": [
              {
                "scopeId": {
                  "Comparison": {
                    "ComparisonKind": 0,
                    "Left": {
                      "Column": {
                        "Expression": {
                          "SourceRef": {
                            "Entity": "Mostaql"
                          }
                        },
                        "Property": "category_arabic"
                      }
                    },
                    "Right": {
                      "Literal": {
                        "Value": "'تطوير الويب'"
                      }
                    }
                  }
                }
              }
            ]
          }
        },
        {
          "properties": {
            "fill": {
              "solid": {
                "color": {
                  "expr": {
                    "Literal": {
                      "Value": "'#9B545B'"
                    }
                  }
                }
              }
            }
          },
          "selector": {
            "data": [
              {
                "scopeId": {
                  "Comparison": {
                    "ComparisonKind": 0,
                    "Left": {
                      "Column": {
                        "Expression": {
                          "SourceRef": {
                            "Entity": "Mostaql"
                          }
                        },
                        "Property": "category_arabic"
                      }
                    },
                    "Right": {
                      "Literal": {
                        "Value": "'تطوير التطبيقات'"
                      }
                    }
                  }
                }
              }
            ]
          }
        },
        {
          "properties": {
            "fill": {
              "solid": {
                "color": {
                  "expr": {
                    "Literal": {
                      "Value": "'#BA7076'"
                    }
                  }
                }
              }
            }
          },
          "selector": {
            "data": [
              {
                "scopeId": {
                  "Comparison": {
                    "ComparisonKind": 0,
                    "Left": {
                      "Column": {
                        "Expression": {
                          "SourceRef": {
                            "Entity": "Mostaql"
                          }
                        },
                        "Property": "category_arabic"
                      }
                    },
                    "Right": {
                      "Literal": {
                        "Value": "'هندسة البرمجيات'"
                      }
                    }
                  }
                }
              }
            ]
          }
        },
        {
          "properties": {
            "fill": {
              "solid": {
                "color": {
                  "expr": {
                    "Literal": {
                      "Value": "'#DA8D93'"
                    }
                  }
                }
              }
            }
          },
          "selector": {
            "data": [
              {
                "scopeId": {
                  "Comparison": {
                    "ComparisonKind": 0,
                    "Left": {
                      "Column": {
                        "Expression": {
                          "SourceRef": {
                            "Entity": "Mostaql"
                          }
                        },
                        "Property": "category_arabic"
                      }
                    },
                    "Right": {
                      "Literal": {
                        "Value": "'علم البيانات'"
                      }
                    }
                  }
                }
              }
            ]
          }
        },
        {
          "properties": {
            "fill": {
              "solid": {
                "color": {
                  "expr": {
                    "Literal": {
                      "Value": "'#FBABB1'"
                    }
                  }
                }
              }
            }
          },
          "selector": {
            "data": [
              {
                "scopeId": {
                  "Comparison": {
                    "ComparisonKind": 0,
                    "Left": {
                      "Column": {
                        "Expression": {
                          "SourceRef": {
                            "Entity": "Mostaql"
                          }
                        },
                        "Property": "category_arabic"
                      }
                    },
                    "Right": {
                      "Literal": {
                        "Value": "'الذكاء الاصطناعي'"
                      }
                    }
                  }
                }
              }
            ]
          }
        },
        {
          "properties": {
            "fill": {
              "solid": {
                "color": {
                  "expr": {
                    "Literal": {
                      "Value": "'#FBABB1'"
                    }
                  }
                }
              }
            }
          },
          "selector": {
            "data": [
              {
                "scopeId": {
                  "Comparison": {
                    "ComparisonKind": 0,
                    "Left": {
                      "Column": {
                        "Expression": {
                          "SourceRef": {
                            "Entity": "Mostaql"
                          }
                        },
                        "Property": "category_arabic"
                      }
                    },
                    "Right": {
                      "Literal": {
                        "Value": "'الذكاء الاصطناعي / تعلم الآلة'"
                      }
                    }
                  }
                }
              }
            ]
          }
        }
      ],
      "labels": [
        {
          "properties": {
            "show": {
              "expr": {
                "Literal": {
                  "Value": "true"
                }
              }
            },
            "labelPosition": {
              "expr": {
                "Literal": {
                  "Value": "'InsideEnd'"
                }
              }
            }
          }
        }
      ]
    },
    "visualContainerObjects": {
      "title": [
        {
          "properties": {
            "titleWrap": {
              "expr": {
                "Literal": {
                  "Value": "true"
                }
              }
            },
            "fontColor": {
              "solid": {
                "color": {
                  "expr": {
                    "Literal": {
                      "Value": "'#3C2F13'"
                    }
                  }
                }
              }
            },
            "fontSize": {
              "expr": {
                "Literal": {
                  "Value": "14D"
                }
              }
            },
            "bold": {
              "expr": {
                "Literal": {
                  "Value": "true"
                }
              }
            },
            "fontFamily": {
              "expr": {
                "Literal": {
                  "Value": "'Arial'"
                }
              }
            },
            "alignment": {
              "expr": {
                "Literal": {
                  "Value": "'right'"
                }
              }
            },
            "text": {
              "expr": {
                "Literal": {
                  "Value": "'عدد الطلب لمهاره '"
                }
              }
            }
          }
        }
      ],
      "background": [
        {
          "properties": {
            "show": {
              "expr": {
                "Literal": {
                  "Value": "true"
                }
              }
            },
            "transparency": {
              "expr": {
                "Literal": {
                  "Value": "0D"
                }
              }
            }
          }
        }
      ],
      "border": [
        {
          "properties": {
            "show": {
              "expr": {
                "Literal": {
                  "Value": "true"
                }
              }
            },
            "color": {
              "solid": {
                "color": {
                  "expr": {
                    "Literal": {
                      "Value": "'#DEAE4A'"
                    }
                  }
                }
              }
            },
            "radius": {
              "expr": {
                "Literal": {
                  "Value": "15D"
                }
              }
            },
            "width": {
              "expr": {
                "Literal": {
                  "Value": "2D"
                }
              }
            }
          }
        }
      ],
      "dropShadow": [
        {
          "properties": {
            "show": {
              "expr": {
                "Literal": {
                  "Value": "true"
                }
              }
            },
            "color": {
              "solid": {
                "color": {
                  "expr": {
                    "ThemeDataColor": {
                      "ColorId": 1,
                      "Percent": 0
                    }
                  }
                }
              }
            }
          }
        }
      ]
    },
    "drillFilterOtherVisuals": true
  },
  "filterConfig": {
    "filters": [
      {
        "name": "c48d134f0c709573a969",
        "field": {
          "Column": {
            "Expression": {
              "SourceRef": {
                "Entity": "Mostaql_Skills"
              }
            },
            "Property": "Tags_en"
          }
        },
        "type": "TopN",
        "filter": {
          "Version": 2,
          "From": [
            {
              "Name": "subquery",
              "Expression": {
                "Subquery": {
                  "Query": {
                    "Version": 2,
                    "From": [
                      {
                        "Name": "m",
                        "Entity": "Mostaql_Skills",
                        "Type": 0
                      }
                    ],
                    "Select": [
                      {
                        "Column": {
                          "Expression": {
                            "SourceRef": {
                              "Source": "m"
                            }
                          },
                          "Property": "Tags_en"
                        },
                        "Name": "field"
                      }
                    ],
                    "OrderBy": [
                      {
                        "Direction": 2,
                        "Expression": {
                          "Aggregation": {
                            "Expression": {
                              "Column": {
                                "Expression": {
                                  "SourceRef": {
                                    "Source": "m"
                                  }
                                },
                                "Property": "Tags_en"
                              }
                            },
                            "Function": 5
                          }
                        }
                      }
                    ],
                    "Top": 9
                  }
                }
              },
              "Type": 2
            },
            {
              "Name": "m",
              "Entity": "Mostaql_Skills",
              "Type": 0
            }
          ],
          "Where": [
            {
              "Condition": {
                "In": {
                  "Expressions": [
                    {
                      "Column": {
                        "Expression": {
                          "SourceRef": {
                            "Source": "m"
                          }
                        },
                        "Property": "Tags_en"
                      }
                    }
                  ],
                  "Table": {
                    "SourceRef": {
                      "Source": "subquery"
                    }
                  }
                }
              }
            }
          ]
        }
      },
      {
        "name": "5dbc1b6f326602024ecc",
        "field": {
          "Column": {
            "Expression": {
              "SourceRef": {
                "Entity": "Mostaql_Skills"
              }
            },
            "Property": "Tags_en"
          }
        },
        "type": "Categorical",
        "filter": {
          "Version": 2,
          "From": [
            {
              "Name": "m",
              "Entity": "Mostaql_Skills",
              "Type": 0
            }
          ],
          "Where": [
            {
              "Condition": {
                "Not": {
                  "Expression": {
                    "In": {
                      "Expressions": [
                        {
                          "Column": {
                            "Expression": {
                              "SourceRef": {
                                "Source": "m"
                              }
                            },
                            "Property": "Tags_en"
                          }
                        }
                      ],
                      "Values": [
                        [
                          {
                            "Literal": {
                              "Value": "'Application development'"
                            }
                          }
                        ],
                        [
                          {
                            "Literal": {
                              "Value": "'Application programming'"
                            }
                          }
                        ],
                        [
                          {
                            "Literal": {
                              "Value": "'Create a website'"
                            }
                          }
                        ],
                        [
                          {
                            "Literal": {
                              "Value": "'Design a website'"
                            }
                          }
                        ],
                        [
                          {
                            "Literal": {
                              "Value": "'Site programming'"
                            }
                          }
                        ],
                        [
                          {
                            "Literal": {
                              "Value": "'Software development'"
                            }
                          }
                        ],
                        [
                          {
                            "Literal": {
                              "Value": "'programming'"
                            }
                          }
                        ],
                        [
                          {
                            "Literal": {
                              "Value": "'Software engineering'"
                            }
                          }
                        ],
                        [
                          {
                            "Literal": {
                              "Value": "'Site design'"
                            }
                          }
                        ],
                        [
                          {
                            "Literal": {
                              "Value": "'Applications design'"
                            }
                          }
                        ]
                      ]
                    }
                  }
                }
              }
            }
          ]
        },
        "howCreated": "User",
        "objects": {
          "general": [
            {
              "properties": {
                "isInvertedSelectionMode": {
                  "expr": {
                    "Literal": {
                      "Value": "true"
                    }
                  }
                }
              }
            }
          ]
        }
      }
    ]
  }
}